copyfiles/__init__.py
copyfiles/cli.py
copyfiles/core.py
copyfiles_cli-0.1.8.dist-info/METADATA
copyfiles_cli-0.1.8.dist-info/WHEEL
copyfiles_cli-0.1.8.dist-info/entry_points.txt
copyfiles_cli-0.1.8.dist-info/top_level.txt
copyfiles_cli-0.1.8.dist-info/RECORD
