Metadata-Version: 2.4
Name: copyfiles-cli
Version: 0.1.8
Summary: Generate a copyfiles.txt containing project tree + file contents.
Author-email: Bethvour <bethvourc@gmail.com>
License: MIT
Project-URL: Homepage, https://github.com/bethvourc/copyf
Project-URL: Documentation, https://github.com/bethvourc/copyf#readme
Project-URL: Changelog, https://github.com/bethvourc/copyf/releases
Keywords: llm,context,project-tree,cli
Requires-Python: >=3.8
Requires-Dist: pathspec>=0.11.0
Requires-Dist: textual>=0.55.0
Requires-Dist: colorama>=0.4.6
Requires-Dist: rich>=13.5
Requires-Dist: rich-argparse>=1.4
Requires-Dist: pyfiglet>=0.8
Provides-Extra: dev
Requires-Dist: pytest>=8.2; extra == "dev"
Requires-Dist: pytest-cov>=5.0; extra == "dev"
Requires-Dist: coverage[toml]>=7.4; extra == "dev"
Requires-Dist: tox>=4.15; extra == "dev"
Requires-Dist: ruff>=0.4; extra == "dev"
Requires-Dist: mypy>=1.10; extra == "dev"
Requires-Dist: pre-commit>=3.7; extra == "dev"
Requires-Dist: build>=1.2.1; extra == "dev"
Requires-Dist: twine>=5.0; extra == "dev"
